pwnelle/__init__.py
pwnelle/analyzer.py
pwnelle/cli.py
pwnelle/main.py
pwnelle/exploiter/__init__.py
pwnelle/exploiter/bof_finder.py
pwnelle/exploiter/exploit_generator.py
pwnelle/exploiter/exploit_tester.py
pwnelle/exploiter/format_string_finder.py
pwnelle/exploiter/heap_overflow_finder.py
pwnelle/gadgets/__init__.py
pwnelle/gadgets/rop_finder.py
pwnelle/report/__init__.py
pwnelle/report/report_generator.py
pwnelle/strings/__init__.py
pwnelle/strings/string_finder.py
pwnelle/templates/__init__.py
pwnelle/templates/template_generator.py
pwnelle/templates/__pycache__/__init__.cpython-310.pyc
pwnelle/templates/__pycache__/__init__.cpython-312.pyc
pwnelle/templates/__pycache__/template_generator.cpython-310.pyc
pwnelle/templates/__pycache__/template_generator.cpython-312.pyc
pwnelle-1.0.4.dist-info/licenses/LICENSE
pwnelle_venv/bin/readelf.py
pwnelle_venv/bin/rpyc_classic.py
pwnelle_venv/bin/rpyc_registry.py
pwnelle-1.0.4.dist-info/METADATA
pwnelle-1.0.4.dist-info/WHEEL
pwnelle-1.0.4.dist-info/entry_points.txt
pwnelle-1.0.4.dist-info/top_level.txt
pwnelle-1.0.4.dist-info/RECORD
