Metadata-Version: 2.4
Name: pwnelle
Version: 1.0.4
Summary: Ultra-fast flag & string hunter for mixed/Unicode encodings
Author-email: EllE961 <yahyaalsalmi961@gmail.com>
License: MIT
Project-URL: Homepage, https://github.com/EllE961/pwnelle
Project-URL: Documentation, https://github.com/EllE961/pwnelle#readme
Project-URL: Issues, https://github.com/EllE961/pwnelle/issues
Project-URL: Source, https://github.com/EllE961/pwnelle
Keywords: security,ctf,binary-analysis,forensics,string-finder
Classifier: Development Status :: 4 - Beta
Classifier: Environment :: Console
Classifier: Intended Audience :: Developers
Classifier: Intended Audience :: Information Technology
Classifier: Intended Audience :: Science/Research
Classifier: License :: OSI Approved :: MIT License
Classifier: Programming Language :: Python :: 3
Classifier: Programming Language :: Python :: 3.9
Classifier: Programming Language :: Python :: 3.10
Classifier: Programming Language :: Python :: 3.11
Classifier: Topic :: Security
Classifier: Topic :: Software Development :: Disassemblers
Classifier: Topic :: Utilities
Requires-Python: >=3.9
License-File: LICENSE
Requires-Dist: typer>=0.12
Requires-Dist: rich>=13.7
Requires-Dist: python-Levenshtein>=0.25
Requires-Dist: pwntools>=4.12
Requires-Dist: capstone>=5.0
Requires-Dist: pyelftools>=0.30
Dynamic: license-file
